gtls/__init__.py
gtls/core.py
gtls/cupyFun.py
gtls/grid.py
gtls/helpers.py
gtls/interpolation.py
gtls/main.py
gtls/stats.py
gtls/tls_constants.py
gtls/transit.py
gtls/validate.py
gputls-0.1.6.dist-info/LICENSE
gputls-0.1.6.dist-info/METADATA
gputls-0.1.6.dist-info/WHEEL
gputls-0.1.6.dist-info/top_level.txt
gputls-0.1.6.dist-info/RECORD
