Metadata-Version: 2.1
Name: gputls
Version: 0.1.6
Summary: A GPU algorithm for speeding up periodic transit detection
Author-email: Quanquan Hu <huquanquan22@mails.ucas.ac.cn>
Maintainer-email: Quanquan Hu <huquanquan22@mails.ucas.ac.cn>
License: MIT License
Project-URL: Homepage, https://github.com/Farthing-0/GTLS
Project-URL: Source, https://github.com/Farthing-0/GTLS
Keywords: astronomy,exoplanet,GPU
Classifier: Development Status :: 3 - Alpha
Classifier: Intended Audience :: Science/Research
Classifier: Topic :: Scientific/Engineering :: Astronomy
Classifier: License :: OSI Approved :: MIT License
Classifier: Programming Language :: Python :: 3
Classifier: Programming Language :: Python :: 3.7
Classifier: Programming Language :: Python :: 3.8
Classifier: Programming Language :: Python :: 3.9
Classifier: Programming Language :: Python :: 3.10
Classifier: Programming Language :: Python :: 3.11
Classifier: Programming Language :: Python :: 3 :: Only
Requires-Python: >=3.6
License-File: LICENSE
Requires-Dist: numpy
Requires-Dist: numba
Requires-Dist: tqdm
Requires-Dist: batman-package
